README.md
setup.py
alibabacloud_ccppath_sdk/__init__.py
alibabacloud_ccppath_sdk/client.py
alibabacloud_ccppath_sdk/models.py
alibabacloud_ccppath_sdk.egg-info/PKG-INFO
alibabacloud_ccppath_sdk.egg-info/SOURCES.txt
alibabacloud_ccppath_sdk.egg-info/dependency_links.txt
alibabacloud_ccppath_sdk.egg-info/requires.txt
alibabacloud_ccppath_sdk.egg-info/top_level.txt